agentic_cli/__init__.py
agentic_cli/config.py
agentic_cli/logging.py
agentic_cli/cli/__init__.py
agentic_cli/cli/app.py
agentic_cli/cli/builtin_commands.py
agentic_cli/cli/commands.py
agentic_cli/knowledge_base/__init__.py
agentic_cli/knowledge_base/embeddings.py
agentic_cli/knowledge_base/manager.py
agentic_cli/knowledge_base/models.py
agentic_cli/knowledge_base/sources.py
agentic_cli/knowledge_base/vector_store.py
agentic_cli/llm/__init__.py
agentic_cli/llm/thinking.py
agentic_cli/persistence/__init__.py
agentic_cli/persistence/artifacts.py
agentic_cli/persistence/session.py
agentic_cli/tools/__init__.py
agentic_cli/tools/executor.py
agentic_cli/tools/registry.py
agentic_cli/tools/resilience.py
agentic_cli/tools/search.py
agentic_cli/tools/standard.py
agentic_cli/workflow/__init__.py
agentic_cli/workflow/config.py
agentic_cli/workflow/events.py
agentic_cli/workflow/manager.py
agentic_cli-0.1.0.dist-info/METADATA
agentic_cli-0.1.0.dist-info/WHEEL
agentic_cli-0.1.0.dist-info/licenses/LICENSE
agentic_cli-0.1.0.dist-info/RECORD
